sphinx_ts/__init__.py
sphinx_ts/directives/__init__.py
sphinx_ts/directives/base.py
sphinx_ts/directives/class_directive.py
sphinx_ts/directives/common.py
sphinx_ts/directives/data_directive.py
sphinx_ts/directives/enum_directive.py
sphinx_ts/directives/interface_directive.py
sphinx_ts/domain.py
sphinx_ts/parser/__init__.py
sphinx_ts/parser/ast_nodes.py
sphinx_ts/parser/doc_comment.py
sphinx_ts/parser/mixins.py
sphinx_ts/parser/ts_parser.py
sphinx_ts/parser/value_parser.py
sphinx_ts/py.typed
sphinx_ts-0.4.0.dist-info/WHEEL
sphinx_ts-0.4.0.dist-info/entry_points.txt
sphinx_ts-0.4.0.dist-info/METADATA
sphinx_ts-0.4.0.dist-info/RECORD
