Metadata-Version: 2.3
Name: sphinx-ts
Version: 0.4.0
Summary: Sphinx extension for TypeScript documentation using Tree-sitter
Keywords: sphinx,typescript,documentation,autodoc,tree-sitter,jsdoc,api-documentation
Author: Thomas Carroll
License: MIT
Classifier: Development Status :: 3 - Alpha
Classifier: Intended Audience :: Developers
Classifier: License :: OSI Approved :: MIT License
Classifier: Programming Language :: Python :: 3
Classifier: Programming Language :: Python :: 3.12
Classifier: Topic :: Documentation
Classifier: Topic :: Documentation :: Sphinx
Classifier: Topic :: Software Development :: Documentation
Classifier: Framework :: Sphinx
Classifier: Framework :: Sphinx :: Extension
Requires-Dist: sphinx>=5.0.0
Requires-Dist: tree-sitter>=0.20.0
Requires-Dist: tree-sitter-typescript>=0.20.0
Requires-Dist: docutils>=0.17
Requires-Dist: sphinx-rtd-theme>=3.0.2
Requires-Dist: furo>=2025.7.19
Maintainer: Thomas Carroll
Requires-Python: >=3.12
Project-URL: Bug Reports, https://github.com/snus-kin/sphinx-ts/issues
Project-URL: Changelog, https://github.com/snus-kin/sphinx-ts/releases
Project-URL: Documentation, https://sphinx-ts.readthedocs.io
Project-URL: Homepage, https://github.com/snus-kin/sphinx-ts
Project-URL: Repository, https://github.com/snus-kin/sphinx-ts
